toeplitzlda/__init__.py
toeplitzlda/classification/__init__.py
toeplitzlda/classification/covariance.py
toeplitzlda/classification/toeplitzlda.py
toeplitzlda/classification/unsupervised.py
toeplitzlda-0.4.1.dist-info/LICENSE
toeplitzlda-0.4.1.dist-info/METADATA
toeplitzlda-0.4.1.dist-info/WHEEL
toeplitzlda-0.4.1.dist-info/RECORD
