Metadata-Version: 2.3
Name: toeplitzlda
Version: 0.4.1
Summary: Implementation of LDA using a block-Toeplitz structured covariance matrix for stationary spatiotemporal data.
License: BSD-3-Clause
Keywords: linear discriminant analysis,spatiotemporal data
Author: Jan Sosulski
Author-email: mail@jan-sosulski.de
Requires-Python: >=3.9,<4.0
Classifier: License :: OSI Approved :: BSD License
Classifier: Programming Language :: Python :: 3
Classifier: Programming Language :: Python :: 3.9
Classifier: Programming Language :: Python :: 3.10
Classifier: Programming Language :: Python :: 3.11
Classifier: Programming Language :: Python :: 3.12
Classifier: Programming Language :: Python :: 3.13
Provides-Extra: solver
Provides-Extra: type-checking
Requires-Dist: blockmatrix (>=0.3,<0.4)
Requires-Dist: mne ; extra == "type-checking"
Requires-Dist: numpy (>=1,<2)
Requires-Dist: scikit-learn (>=1,<2)
Requires-Dist: toeplitz (==0.3.2) ; extra == "solver"
Project-URL: Homepage, https://github.com/jsosulski/toeplitzlda
Project-URL: Preprint, https://arxiv.org/abs/2202.02001
Project-URL: Repository, https://github.com/jsosulski/toeplitzlda
